{
  "isStruct": false,
  "key": [
    "id"
  ],
  "semantic": "region| |area|, |place|, |street|, ะด.|house|, |building",
  "name": "address",
  "version": "",
  "caption": "Address",
  "ancestor": null,
  "container": null,
  "creationTracker": "",
  "changeTracker": "",
  "history": 0,
  "journaling": false,
  "compositeIndexes": [],
  "properties": [
    {
      "orderNumber": 10,
      "name": "id",
      "caption": "ID",
      "type": 12,
      "size": 24,
      "decimals": 0,
      "allowedFileTypes": null,
      "maxFileCount": 0,
      "nullable": false,
      "readonly": true,
      "indexed": false,
      "unique": true,
      "autoassigned": true,
      "hint": null,
      "defaultValue": null,
      "refClass": "",
      "itemsClass": "",
      "backRef": "",
      "backColl": "",
      "binding": "",
      "semantic": null,
      "selConditions": [],
      "selSorting": [],
      "selectionProvider": null,
      "indexSearch": false,
      "eagerLoading": false,
      "formula": null
    },
    {
      "orderNumber": 56,
      "name": "place",
      "caption": "Locality",
      "type": 0,
      "size": null,
      "decimals": 0,
      "allowedFileTypes": null,
      "maxFileCount": 0,
      "nullable": true,
      "readonly": false,
      "indexed": true,
      "unique": false,
      "autoassigned": false,
      "hint": null,
      "defaultValue": null,
      "refClass": null,
      "itemsClass": "",
      "backRef": "",
      "backColl": "",
      "binding": "",
      "semantic": "",
      "selConditions": [],
      "selSorting": [],
      "selectionProvider": null,
      "indexSearch": false,
      "eagerLoading": false,
      "formula": null
    },
    {
      "orderNumber": 58,
      "name": "street",
      "caption": "Street",
      "type": 0,
      "size": null,
      "decimals": 0,
      "allowedFileTypes": null,
      "maxFileCount": 0,
      "nullable": true,
      "readonly": false,
      "indexed": true,
      "unique": false,
      "autoassigned": false,
      "hint": null,
      "defaultValue": null,
      "refClass": "street",
      "itemsClass": "",
      "backRef": "",
      "backColl": "",
      "binding": "",
      "semantic": null,
      "selConditions": [],
      "selSorting": [],
      "selectionProvider": null,
      "indexSearch": false,
      "eagerLoading": false,
      "formula": null
    },
    {
      "orderNumber": 70,
      "name": "house",
      "caption": "House",
      "type": 0,
      "size": null,
      "decimals": 0,
      "allowedFileTypes": null,
      "maxFileCount": 0,
      "nullable": true,
      "readonly": false,
      "indexed": true,
      "unique": false,
      "autoassigned": false,
      "hint": null,
      "defaultValue": null,
      "refClass": "",
      "itemsClass": "",
      "backRef": "",
      "backColl": "",
      "binding": "",
      "semantic": null,
      "selConditions": [],
      "selSorting": [],
      "selectionProvider": null,
      "indexSearch": false,
      "eagerLoading": false,
      "formula": null
    },
    {
      "orderNumber": 75,
      "name": "building",
      "caption": "Building (letter)",
      "type": 0,
      "size": null,
      "decimals": 0,
      "allowedFileTypes": null,
      "maxFileCount": 0,
      "nullable": true,
      "readonly": false,
      "indexed": true,
      "unique": false,
      "autoassigned": false,
      "hint": null,
      "defaultValue": null,
      "refClass": "",
      "itemsClass": "",
      "backRef": "",
      "backColl": "",
      "binding": "",
      "semantic": null,
      "selConditions": [],
      "selSorting": [],
      "selectionProvider": null,
      "indexSearch": false,
      "eagerLoading": false,
      "formula": null
    },
    {
      "orderNumber": 80,
      "name": "flat",
      "caption": "Apartment",
      "type": 0,
      "size": null,
      "decimals": 0,
      "allowedFileTypes": null,
      "maxFileCount": 0,
      "nullable": true,
      "readonly": false,
      "indexed": true,
      "unique": false,
      "autoassigned": false,
      "hint": null,
      "defaultValue": null,
      "refClass": "",
      "itemsClass": "",
      "backRef": "",
      "backColl": "",
      "binding": "",
      "semantic": null,
      "selConditions": [],
      "selSorting": [],
      "selectionProvider": null,
      "indexSearch": false,
      "eagerLoading": false,
      "formula": null
    },
    {
      "orderNumber": 80,
      "name": "adressValue",
      "caption": "Address, if there are no values in the catalogs",
      "type": 0,
      "size": 128,
      "decimals": 0,
      "allowedFileTypes": null,
      "maxFileCount": 0,
      "nullable": true,
      "readonly": false,
      "indexed": true,
      "unique": false,
      "autoassigned": false,
      "hint": null,
      "defaultValue": null,
      "refClass": "",
      "itemsClass": "",
      "backRef": "",
      "backColl": "",
      "binding": "",
      "semantic": null,
      "selConditions": [],
      "selSorting": [],
      "selectionProvider": null,
      "indexSearch": false,
      "eagerLoading": false,
      "formula": null
    },
    {
      "orderNumber": 80,
      "name": "adressFormula",
      "caption": "Address [computable]",
      "type": 0,
      "size": 128,
      "decimals": 0,
      "allowedFileTypes": null,
      "maxFileCount": 0,
      "nullable": true,
      "readonly": false,
      "indexed": true,
      "unique": false,
      "autoassigned": false,
      "hint": null,
      "defaultValue": null,
      "refClass": "",
      "itemsClass": "",
      "backRef": "",
      "backColl": "",
      "binding": "",
      "semantic": null,
      "selConditions": [],
      "selSorting": [],
      "selectionProvider": null,
      "indexSearch": false,
      "eagerLoading": false,
      "formula": {
        "concat": [
          {
            "if": [
              "$area",
              "$area",
              ""
            ]
          },
          ", ",
          {
            "if": [
              "$place",
              "$place",
              ""
            ]
          },
          ", ",
          {
            "if": [
              "$street",
              "$street",
              ""
            ]
          },
          ", ",
          {
            "if": [
              "$house",
              "$house",
              ""
            ]
          },
          ", ",
          {
            "if": [
              "$flat",
              "$flat",
              ""
            ]
          }
        ]
      },
      "cached": true
    },
    {
      "orderNumber": 40,
      "name": "area",
      "caption": "District",
      "type": 0,
      "size": null,
      "decimals": 0,
      "allowedFileTypes": null,
      "maxFileCount": 0,
      "nullable": true,
      "readonly": false,
      "indexed": true,
      "unique": false,
      "autoassigned": false,
      "hint": null,
      "defaultValue": null,
      "refClass": "",
      "itemsClass": "",
      "backRef": "",
      "backColl": "",
      "binding": "",
      "semantic": null,
      "selConditions": [],
      "selSorting": [],
      "selectionProvider": null,
      "indexSearch": false,
      "eagerLoading": false,
      "formula": null
    },
    {
      "orderNumber": 30,
      "name": "region",
      "caption": "Region",
      "type": 0,
      "size": null,
      "decimals": 0,
      "allowedFileTypes": null,
      "maxFileCount": 0,
      "nullable": true,
      "readonly": false,
      "indexed": true,
      "unique": false,
      "autoassigned": false,
      "hint": null,
      "defaultValue": null,
      "refClass": "",
      "itemsClass": "",
      "backRef": "",
      "backColl": "",
      "binding": "",
      "semantic": null,
      "selConditions": [],
      "selSorting": [],
      "selectionProvider": null,
      "indexSearch": false,
      "eagerLoading": false,
      "formula": null
    },
    {
      "orderNumber": 50,
      "name": "index",
      "caption": "Postcode",
      "type": 6,
      "size": null,
      "decimals": 0,
      "allowedFileTypes": null,
      "maxFileCount": 0,
      "nullable": true,
      "readonly": false,
      "indexed": true,
      "unique": false,
      "autoassigned": false,
      "hint": null,
      "defaultValue": null,
      "refClass": "",
      "itemsClass": "",
      "backRef": "",
      "backColl": "",
      "binding": "",
      "semantic": null,
      "selConditions": [],
      "selSorting": [],
      "selectionProvider": null,
      "indexSearch": false,
      "eagerLoading": false,
      "formula": null
    }
  ],
  "metaVersion": "2.0.61.15690"
}